Metadata-Version: 2.1
Name: pyslvSudoku
Version: 0.1
Summary: Simple package fro solving a sudoku
Author: Subhradipta Paul
Author-email: paulsubhradipta@gmail.com
License: MIT
Keywords: sudoku
Classifier: Development Status :: 3 - Alpha
Classifier: Intended Audience :: Developers
Classifier: Topic :: Software Development :: Build Tools
Classifier: License :: OSI Approved :: MIT License
Classifier: Programming Language :: Python :: 3
Classifier: Programming Language :: Python :: 3.4
Classifier: Programming Language :: Python :: 3.5
Classifier: Programming Language :: Python :: 3.6
Classifier: Programming Language :: Python :: 3.7
License-File: LICENSE.txt
